accounting_subject_analysis_mcp_server/__init__.py
accounting_subject_analysis_mcp_server/config/kb.json
accounting_subject_analysis_mcp_server-0.1.4.dist-info/METADATA
accounting_subject_analysis_mcp_server-0.1.4.dist-info/WHEEL
accounting_subject_analysis_mcp_server-0.1.4.dist-info/entry_points.txt
accounting_subject_analysis_mcp_server-0.1.4.dist-info/licenses/LICENSE
accounting_subject_analysis_mcp_server-0.1.4.dist-info/RECORD
