Metadata-Version: 2.4
Name: accounting-subject-analysis-mcp-server
Version: 0.1.4
Summary: MCP Server for Accounting Subject Analysis Method - 提供根据科目/指标名称获取分析方法和输出样例的工具
Author-email: Fang Jian <fangjian@vip.sina.com>
License: MIT
License-File: LICENSE
Keywords: accounting,financial-analysis,mcp,model-context-protocol
Classifier: Development Status :: 4 - Beta
Classifier: Intended Audience :: Developers
Classifier: License :: OSI Approved :: MIT License
Classifier: Programming Language :: Python :: 3
Classifier: Programming Language :: Python :: 3.8
Classifier: Programming Language :: Python :: 3.9
Classifier: Programming Language :: Python :: 3.10
Classifier: Programming Language :: Python :: 3.11
Classifier: Programming Language :: Python :: 3.12
Requires-Python: >=3.8
Requires-Dist: fastmcp
